brynq_sdk_zucchetti/__init__.py
brynq_sdk_zucchetti/client.py
brynq_sdk_zucchetti/employment.py
brynq_sdk_zucchetti/subject.py
brynq_sdk_zucchetti/zucchetti.py
brynq_sdk_zucchetti/schemas/__init__.py
brynq_sdk_zucchetti/schemas/employment_schema.py
brynq_sdk_zucchetti/schemas/enums.py
brynq_sdk_zucchetti/schemas/subject_schema.py
brynq_sdk_zucchetti-1.0.5.dist-info/METADATA
brynq_sdk_zucchetti-1.0.5.dist-info/WHEEL
brynq_sdk_zucchetti-1.0.5.dist-info/top_level.txt
brynq_sdk_zucchetti-1.0.5.dist-info/RECORD
