Metadata-Version: 2.4
Name: brynq_sdk_zucchetti
Version: 1.0.5
Summary: Zucchetti HR PERSONAL DATA import wrapper from BrynQ
Author: BrynQ
Author-email: support@brynq.com
License: BrynQ License
Requires-Dist: requests<=3,>=2
Requires-Dist: pydantic<3,>=2
Requires-Dist: pandas<3.0.0,>=2.2.0
Requires-Dist: zeep<5.0.0,>=4.0.0
Dynamic: author
Dynamic: author-email
Dynamic: description
Dynamic: license
Dynamic: requires-dist
Dynamic: summary
